pyside_ui_backpack/__init__.py
pyside_ui_backpack/css/__init__.py
pyside_ui_backpack/css/colors.py
pyside_ui_backpack/css/css_push_button.py
pyside_ui_backpack/css/css_widgets.py
pyside_ui_backpack/dialogs/__init__.py
pyside_ui_backpack/dialogs/dialogs.py
pyside_ui_backpack/test/__init__.py
pyside_ui_backpack/test/test_css_button.py
pyside_ui_backpack/test/test_css_button_pyside6.py
pyside_ui_backpack/test/test_dialogs.py
pyside_ui_backpack/test/test_dialogs_pyside6.py
pyside_ui_backpack/test/test_push_button.py
pyside_ui_backpack/test/test_push_button_pyside6.py
pyside_ui_backpack/test/test_wait_cursor.py
pyside_ui_backpack/test/test_wait_cursor_pyside6.py
pyside_ui_backpack/version.py
pyside_ui_backpack/widgets/__init__.py
pyside_ui_backpack/widgets/push_button.py
pyside_ui_backpack/widgets/wait_cursor.py
pyside_ui_backpack-1.0.6.dist-info/LICENSE
pyside_ui_backpack-1.0.6.dist-info/METADATA
pyside_ui_backpack-1.0.6.dist-info/WHEEL
pyside_ui_backpack-1.0.6.dist-info/RECORD
