Metadata-Version: 2.1
Name: pyside-ui-backpack
Version: 1.0.6
Summary: Helper functions for PySide2 UI Widgets
Home-page: https://github.com/MaxRocamora/ps-ui-backpack
License: MIT
Author: Maximilliano Rocamora
Author-email: maxirocamora@gmail.com
Requires-Python: >=3.7,<3.14
Classifier: Intended Audience :: Developers
Classifier: License :: OSI Approved :: MIT License
Classifier: Operating System :: OS Independent
Classifier: Programming Language :: Python :: 3
Classifier: Programming Language :: Python :: 3.7
Classifier: Programming Language :: Python :: 3.8
Classifier: Programming Language :: Python :: 3.9
Classifier: Programming Language :: Python :: 3.10
Classifier: Programming Language :: Python :: 3.11
Classifier: Programming Language :: Python :: 3.12
Classifier: Programming Language :: Python :: 3.13
